[
  {
    "code": "001",
    "nom": "Commune 1",
    "contour": {
      "type": "Polygon",
      "coordinates": [
        [
          [-1.5, 48.0],
          [-1.4, 48.0],
          [-1.4, 48.1],
          [-1.5, 48.1],
          [-1.5, 48.0]
        ]
      ]
    }
  },
  {
    "code": "002",
    "nom": "Commune 2",
    "contour": {
      "type": "Polygon",
      "coordinates": [
        [
          [-1.4, 48.0],
          [-1.3, 48.0],
          [-1.3, 48.1],
          [-1.4, 48.1],
          [-1.4, 48.0]
        ]
      ]
    }
  },
  {
    "code": "003",
    "nom": "Commune 3",
    "contour": {
      "type": "Polygon",
      "coordinates": [
        [
          [-1.3, 48.0],
          [-1.2, 48.0],
          [-1.2, 48.1],
          [-1.3, 48.1],
          [-1.3, 48.0]
        ]
      ]
    }
  }
]
